{
    "shop":[
        {
            "id":1,
            "img":"https://github.com/hetuk2005/webDevelopment/blob/main/Utils/Bag%201.jpg?raw=true",
            "title":"Vintage Outdoor Canvas Backpack"
        },
        {
            "id":2,
            "img":"https://github.com/hetuk2005/webDevelopment/blob/main/Utils/Bag%202.jpg?raw=true",
            "title":"Modern Black Urban Backpack"
        },
        {
            "id":3,
            "img":"https://github.com/hetuk2005/webDevelopment/blob/main/Utils/Bag%203.jpg?raw=true",
            "title":"Minimalist Black Travel Backpack"
        },
        {
            "id":4,
            "img":"https://github.com/hetuk2005/webDevelopment/blob/main/Utils/Bag%204.jpg?raw=true",
            "title":"Brown Leather Casual Backpack"
        },
        {
            "id":5,
            "img":"https://github.com/hetuk2005/webDevelopment/blob/main/Utils/Bag%205.jpg?raw=true",
            "title":"Haupes Hunter Green Rucksack"
        },
        {
            "id":6,
            "img":"https://github.com/hetuk2005/webDevelopment/blob/main/Utils/Bag%206.jpg?raw=true",
            "title":"Classic Vinta Canvas Backpack"
        },
        {
            "id":7,
            "img":"https://github.com/hetuk2005/webDevelopment/blob/main/Utils/Bag%207.jpg?raw=true",
            "title":"Byork Woven Rattan Backpack"
        },
        {
            "id":8,
            "img":"https://github.com/hetuk2005/webDevelopment/blob/main/Utils/Bag%208.jpg?raw=true",
            "title":"Olive Drab Adventurer"
        },
        {
            "id":9,
            "img":"https://github.com/hetuk2005/webDevelopment/blob/main/Utils/Bag%209.jpg?raw=true",
            "title":"Haupes Classic Flap Backpack"
        },
        {
            "id":10,
            "img":"https://github.com/hetuk2005/webDevelopment/blob/main/Utils/Bag%2010.jpg?raw=true",
            "title":"Maroon Canvas Rolltop"
        },
        {
            "id":11,
            "img":"https://github.com/hetuk2005/webDevelopment/blob/main/Utils/Bag%2011.jpg?raw=true",
            "title":"Last Craft Two-Tone Heritage Rucksack"
        },
        {
            "id":12,
            "img":"https://github.com/hetuk2005/webDevelopment/blob/main/Utils/Bag%2012.jpg?raw=true",
            "title":"White Elephant Print Backpack"
        },
        {
            "id":13,
            "img":"https://github.com/hetuk2005/webDevelopment/blob/main/Utils/Bag%2013.jpg?raw=true",
            "title":"Fjallraven Black Rolltop Backpack"
        }
    ]
}